xiaofeig/__init__.py
xiaofeig/example.py
xiaofeig-0.0.2.dist-info/METADATA
xiaofeig-0.0.2.dist-info/WHEEL
xiaofeig-0.0.2.dist-info/RECORD
