Metadata-Version: 2.4
Name: xiaofeig
Version: 0.0.2
Requires-Dist: requests==2.32.4
